{"_internal":{"pubDateTime":"2020-03-05 14:20:35.865 EST","igorPath":"S3,1583436020697,1583436030790|nbads,1583436030790,1583436031057|poller16,1583436035225,1583436035264|router,1583436035264,1583436035268|domUpdater,1583436035269,1583436035766|feedProducer,1583436035766,1583436035893","routeName":"boxscore","routeValue":"S3::2019_20191216/linescores/0021900400.xml","xslt":"NBA/xsl/date/scoreboard/marty_daily_scoreboard.xsl","xsltForceRecompile":"true","xsltInCache":"false","xsltCompileTimeMillis":"66","xsltTransformTimeMillis":"29","consolidatedDomKey":"prod__transform__marty_daily_scoreboard__4410799132597","endToEndTimeMillis":"15196"},"numGames":7,"games":[{"seasonStageId":2,"seasonYear":"2019","leagueName":"standard","gameId":"0021900394","arena":{"name":"Little Caesars Arena","isDomestic":true,"city":"Detroit","stateAbbr":"MI","country":"USA"},"isGameActivated":false,"statusNum":3,"extendedStatusNum":0,"startTimeEastern":"7:00 PM ET","startTimeUTC":"2019-12-17T00:00:00.000Z","endTimeUTC":"2019-12-17T02:37:00.000Z","startDateEastern":"20191216","homeStartDate":"20191216","homeStartTime":"1900","visitorStartDate":"20191216","visitorStartTime":"1900","gameUrlCode":"20191216/WASDET","clock":"","isBuzzerBeater":false,"isPreviewArticleAvail":true,"isRecapArticleAvail":true,"nugget":{"text":"Beal: 35 pts, 10 ast | Thomas: 23 pts"},"attendance":"14632","tickets":{"mobileApp":"https://a.data.nba.com/tickets/single/2019/0021900394/APP_TIX","desktopWeb":"https://a.data.nba.com/tickets/single/2019/0021900394/TEAM_SCH","mobileWeb":"https://a.data.nba.com/tickets/single/2019/0021900394/WEB_MWEB","leagGameInfo":"https://a.data.nba.com/tickets/single/2019/0021900394/LEAG_GAMEINFO","leagTix":"https://a.data.nba.com/tickets/single/2019/0021900394/LEAG_TIX"},"hasGameBookPdf":true,"isStartTimeTBD":false,"gameDuration":{"hours":"2","minutes":"25"},"period":{"current":4,"type":0,"maxRegular":4,"isHalftime":false,"isEndOfPeriod":false},"vTeam":{"teamId":"1610612764","triCode":"WAS","win":"8","loss":"17","seriesWin":"2","seriesLoss":"0","score":"133","linescore":[{"score":"43"},{"score":"24"},{"score":"29"},{"score":"37"}]},"hTeam":{"teamId":"1610612765","triCode":"DET","win":"11","loss":"16","seriesWin":"0","seriesLoss":"2","score":"119","linescore":[{"score":"31"},{"score":"30"},{"score":"30"},{"score":"28"}]},"watch":{"broadcast":{"broadcasters":{"national":[],"canadian":[],"vTeam":[{"shortName":"NBCSWA+","longName":"NBC SPORTS WASHINGTON PLUS"}],"hTeam":[{"shortName":"FSD","longName":"Fox Sports Detroit"}],"spanish_hTeam":[],"spanish_vTeam":[],"spanish_national":[]},"video":{"regionalBlackoutCodes":"","canPurchase":true,"isLeaguePass":true,"isNationalBlackout":false,"isTNTOT":false,"isVR":false,"tntotIsOnAir":false,"isNextVR":false,"isNBAOnTNTVR":false,"isMagicLeap":false,"isOculusVenues":false,"streams":[{"streamType":"vTeam","isOnAir":false,"doesArchiveExist":true,"isArchiveAvailToWatch":true,"streamId":"100219003941220","duration":0},{"streamType":"hTeam","isOnAir":false,"doesArchiveExist":true,"isArchiveAvailToWatch":true,"streamId":"100219003941120","duration":0},{"streamType":"espanol_vTeam","isOnAir":false,"doesArchiveExist":false,"isArchiveAvailToWatch":false,"streamId":"","duration":0},{"streamType":"espanol_hTeam","isOnAir":false,"doesArchiveExist":false,"isArchiveAvailToWatch":false,"streamId":"","duration":0},{"streamType":"espanol_natl","isOnAir":false,"doesArchiveExist":false,"isArchiveAvailToWatch":false,"streamId":"","duration":0},{"streamType":"mobile","isOnAir":false,"doesArchiveExist":true,"isArchiveAvailToWatch":true,"streamId":"100219003941320","duration":0},{"streamType":"condensed","isOnAir":false,"doesArchiveExist":true,"isArchiveAvailToWatch":true,"streamId":"100219003941030","duration":0},{"streamType":"alt","isOnAir":false,"doesArchiveExist":false,"isArchiveAvailToWatch":false,"streamId":"","duration":0}],"deepLink":[]},"audio":{"national":{"streams":[{"language":"English","isOnAir":false,"streamId":""},{"language":"Spanish","isOnAir":false,"streamId":""}],"broadcasters":[]},"vTeam":{"streams":[{"language":"English","isOnAir":true,"streamId":"100219003942211"},{"language":"Spanish","isOnAir":false,"streamId":""}],"broadcasters":[{"shortName":"1500 AM","longName":"1500 AM"}]},"hTeam":{"streams":[{"language":"English","isOnAir":true,"streamId":"100219003942111"},{"language":"Spanish","isOnAir":false,"streamId":""}],"broadcasters":[{"shortName":"97.1 FM The Ticket","longName":"97.1 FM The Ticket"}]}}}}},{"seasonStageId":2,"seasonYear":"2019","leagueName":"standard","gameId":"0021900395","arena":{"name":"Scotiabank Arena","isDomestic":false,"city":"Toronto","stateAbbr":"ON","country":"Canada"},"isGameActivated":false,"statusNum":3,"extendedStatusNum":0,"startTimeEastern":"7:30 PM ET","startTimeUTC":"2019-12-17T00:30:00.000Z","endTimeUTC":"2019-12-17T02:38:00.000Z","startDateEastern":"20191216","homeStartDate":"20191216","homeStartTime":"1930","visitorStartDate":"20191216","visitorStartTime":"1930","gameUrlCode":"20191216/CLETOR","clock":"","isBuzzerBeater":false,"isPreviewArticleAvail":true,"isRecapArticleAvail":true,"nugget":{"text":"Siakam: 33 pts | Lowry: 20 pts, 11 ast"},"attendance":"19800","tickets":{"mobileApp":"https://a.data.nba.com/tickets/single/2019/0021900395/APP_TIX","desktopWeb":"https://a.data.nba.com/tickets/single/2019/0021900395/TEAM_SCH","mobileWeb":"https://a.data.nba.com/tickets/single/2019/0021900395/WEB_MWEB","leagGameInfo":"https://a.data.nba.com/tickets/single/2019/0021900395/LEAG_GAMEINFO","leagTix":"https://a.data.nba.com/tickets/single/2019/0021900395/LEAG_TIX"},"hasGameBookPdf":true,"isStartTimeTBD":false,"gameDuration":{"hours":"1","minutes":"57"},"period":{"current":4,"type":0,"maxRegular":4,"isHalftime":false,"isEndOfPeriod":false},"vTeam":{"teamId":"1610612739","triCode":"CLE","win":"6","loss":"21","seriesWin":"0","seriesLoss":"1","score":"113","linescore":[{"score":"29"},{"score":"25"},{"score":"30"},{"score":"29"}]},"hTeam":{"teamId":"1610612761","triCode":"TOR","win":"18","loss":"8","seriesWin":"1","seriesLoss":"0","score":"133","linescore":[{"score":"37"},{"score":"29"},{"score":"38"},{"score":"29"}]},"watch":{"broadcast":{"broadcasters":{"national":[],"canadian":[{"shortName":"SN1","longName":"SN1"}],"vTeam":[{"shortName":"FSO","longName":"Fox Sports Ohio"}],"hTeam":[{"shortName":"SN1","longName":"SN1"}],"spanish_hTeam":[],"spanish_vTeam":[],"spanish_national":[]},"video":{"regionalBlackoutCodes":"","canPurchase":true,"isLeaguePass":true,"isNationalBlackout":false,"isTNTOT":false,"isVR":false,"tntotIsOnAir":false,"isNextVR":false,"isNBAOnTNTVR":false,"isMagicLeap":false,"isOculusVenues":false,"streams":[{"streamType":"vTeam","isOnAir":false,"doesArchiveExist":true,"isArchiveAvailToWatch":true,"streamId":"100219003951220","duration":0},{"streamType":"hTeam","isOnAir":false,"doesArchiveExist":true,"isArchiveAvailToWatch":true,"streamId":"100219003951120","duration":0},{"streamType":"espanol_vTeam","isOnAir":false,"doesArchiveExist":false,"isArchiveAvailToWatch":false,"streamId":"","duration":0},{"streamType":"espanol_hTeam","isOnAir":false,"doesArchiveExist":false,"isArchiveAvailToWatch":false,"streamId":"","duration":0},{"streamType":"espanol_natl","isOnAir":false,"doesArchiveExist":false,"isArchiveAvailToWatch":false,"streamId":"","duration":0},{"streamType":"mobile","isOnAir":false,"doesArchiveExist":true,"isArchiveAvailToWatch":true,"streamId":"100219003951320","duration":0},{"streamType":"condensed","isOnAir":false,"doesArchiveExist":true,"isArchiveAvailToWatch":true,"streamId":"100219003951030","duration":0},{"streamType":"alt","isOnAir":false,"doesArchiveExist":false,"isArchiveAvailToWatch":false,"streamId":"","duration":0}],"deepLink":[]},"audio":{"national":{"streams":[{"language":"English","isOnAir":false,"streamId":""},{"language":"Spanish","isOnAir":false,"streamId":""}],"broadcasters":[]},"vTeam":{"streams":[{"language":"English","isOnAir":true,"streamId":"100219003952211"},{"language":"Spanish","isOnAir":true,"streamId":"100219003952212"}],"broadcasters":[{"shortName":"WTAM 1100 / 100.7 WMMS / 87.7 FM (ESP)","longName":"WTAM 1100 / 100.7 WMMS / 87.7 FM (ESP)"}]},"hTeam":{"streams":[{"language":"English","isOnAir":true,"streamId":"100219003952111"},{"language":"Spanish","isOnAir":false,"streamId":""}],"broadcasters":[{"shortName":"Sportsnet 590 The FAN","longName":"Sportsnet 590 The FAN"}]}}}}},{"seasonStageId":2,"seasonYear":"2019","leagueName":"standard","gameId":"0021900396","arena":{"name":"Toyota Center","isDomestic":true,"city":"Houston","stateAbbr":"TX","country":"USA"},"isGameActivated":false,"statusNum":3,"extendedStatusNum":0,"startTimeEastern":"8:00 PM ET","startTimeUTC":"2019-12-17T01:00:00.000Z","endTimeUTC":"2019-12-17T03:29:00.000Z","startDateEastern":"20191216","homeStartDate":"20191216","homeStartTime":"1900","visitorStartDate":"20191216","visitorStartTime":"1900","gameUrlCode":"20191216/SASHOU","clock":"","isBuzzerBeater":false,"isPreviewArticleAvail":true,"isRecapArticleAvail":true,"nugget":{"text":"Westbrook: 31 pts | HOU: Overcomes 25-pt deficit"},"attendance":"18055","tickets":{"mobileApp":"https://a.data.nba.com/tickets/single/2019/0021900396/APP_TIX","desktopWeb":"https://a.data.nba.com/tickets/single/2019/0021900396/TEAM_SCH","mobileWeb":"https://a.data.nba.com/tickets/single/2019/0021900396/WEB_MWEB","leagGameInfo":"https://a.data.nba.com/tickets/single/2019/0021900396/LEAG_GAMEINFO","leagTix":"https://a.data.nba.com/tickets/single/2019/0021900396/LEAG_TIX"},"hasGameBookPdf":true,"isStartTimeTBD":false,"gameDuration":{"hours":"2","minutes":"18"},"period":{"current":4,"type":0,"maxRegular":4,"isHalftime":false,"isEndOfPeriod":false},"vTeam":{"teamId":"1610612759","triCode":"SAS","win":"10","loss":"16","seriesWin":"1","seriesLoss":"1","score":"107","linescore":[{"score":"35"},{"score":"37"},{"score":"17"},{"score":"18"}]},"hTeam":{"teamId":"1610612745","triCode":"HOU","win":"18","loss":"9","seriesWin":"1","seriesLoss":"1","score":"109","linescore":[{"score":"21"},{"score":"32"},{"score":"30"},{"score":"26"}]},"watch":{"broadcast":{"broadcasters":{"national":[],"canadian":[{"shortName":"TSN.CA/App","longName":"TSN.ca & TSN App"}],"vTeam":[{"shortName":"KENS","longName":"KENS"}],"hTeam":[{"shortName":"ATTSN-SW","longName":"AT&T Sportsnet - Southwest"}],"spanish_hTeam":[],"spanish_vTeam":[],"spanish_national":[]},"video":{"regionalBlackoutCodes":"","canPurchase":true,"isLeaguePass":true,"isNationalBlackout":false,"isTNTOT":false,"isVR":false,"tntotIsOnAir":false,"isNextVR":false,"isNBAOnTNTVR":false,"isMagicLeap":false,"isOculusVenues":false,"streams":[{"streamType":"vTeam","isOnAir":false,"doesArchiveExist":true,"isArchiveAvailToWatch":true,"streamId":"100219003961220","duration":0},{"streamType":"hTeam","isOnAir":false,"doesArchiveExist":true,"isArchiveAvailToWatch":true,"streamId":"100219003961120","duration":0},{"streamType":"espanol_vTeam","isOnAir":false,"doesArchiveExist":false,"isArchiveAvailToWatch":false,"streamId":"","duration":0},{"streamType":"espanol_hTeam","isOnAir":false,"doesArchiveExist":false,"isArchiveAvailToWatch":false,"streamId":"","duration":0},{"streamType":"espanol_natl","isOnAir":false,"doesArchiveExist":false,"isArchiveAvailToWatch":false,"streamId":"","duration":0},{"streamType":"mobile","isOnAir":false,"doesArchiveExist":true,"isArchiveAvailToWatch":true,"streamId":"100219003961320","duration":0},{"streamType":"condensed","isOnAir":false,"doesArchiveExist":true,"isArchiveAvailToWatch":true,"streamId":"100219003961030","duration":0},{"streamType":"alt","isOnAir":false,"doesArchiveExist":false,"isArchiveAvailToWatch":false,"streamId":"","duration":0}],"deepLink":[]},"audio":{"national":{"streams":[{"language":"English","isOnAir":false,"streamId":""},{"language":"Spanish","isOnAir":false,"streamId":""}],"broadcasters":[]},"vTeam":{"streams":[{"language":"English","isOnAir":true,"streamId":"100219003962211"},{"language":"Spanish","isOnAir":true,"streamId":"100219003962212"}],"broadcasters":[{"shortName":"WOAI 1200AM | S: KTXN 1350AM / 107.5FM H","longName":"WOAI 1200AM | S: KTXN 1350AM / 107.5FM H"}]},"hTeam":{"streams":[{"language":"English","isOnAir":true,"streamId":"100219003962111"},{"language":"Spanish","isOnAir":true,"streamId":"100219003962112"}],"broadcasters":[{"shortName":"790 KBME & 740 KTRH / 850 KEYH & 101.7 F","longName":"790 KBME & 740 KTRH / 850 KEYH & 101.7 F"}]}}}}},{"seasonStageId":2,"seasonYear":"2019","leagueName":"standard","gameId":"0021900397","arena":{"name":"FedExForum","isDomestic":true,"city":"Memphis","stateAbbr":"TN","country":"USA"},"isGameActivated":false,"statusNum":3,"extendedStatusNum":0,"startTimeEastern":"8:00 PM ET","startTimeUTC":"2019-12-17T01:00:00.000Z","endTimeUTC":"2019-12-17T03:32:00.000Z","startDateEastern":"20191216","homeStartDate":"20191216","homeStartTime":"1900","visitorStartDate":"20191216","visitorStartTime":"2000","gameUrlCode":"20191216/MIAMEM","clock":"","isBuzzerBeater":false,"isPreviewArticleAvail":true,"isRecapArticleAvail":true,"nugget":{"text":"Morant: 20 points, 10 assists"},"attendance":"14021","tickets":{"mobileApp":"https://a.data.nba.com/tickets/single/2019/0021900397/APP_TIX","desktopWeb":"https://a.data.nba.com/tickets/single/2019/0021900397/TEAM_SCH","mobileWeb":"https://a.data.nba.com/tickets/single/2019/0021900397/WEB_MWEB","leagGameInfo":"https://a.data.nba.com/tickets/single/2019/0021900397/LEAG_GAMEINFO","leagTix":"https://a.data.nba.com/tickets/single/2019/0021900397/LEAG_TIX"},"hasGameBookPdf":true,"isStartTimeTBD":false,"gameDuration":{"hours":"2","minutes":"21"},"period":{"current":4,"type":0,"maxRegular":4,"isHalftime":false,"isEndOfPeriod":false},"vTeam":{"teamId":"1610612748","triCode":"MIA","win":"19","loss":"8","seriesWin":"1","seriesLoss":"1","score":"111","linescore":[{"score":"32"},{"score":"26"},{"score":"28"},{"score":"25"}]},"hTeam":{"teamId":"1610612763","triCode":"MEM","win":"10","loss":"17","seriesWin":"1","seriesLoss":"1","score":"118","linescore":[{"score":"36"},{"score":"37"},{"score":"22"},{"score":"23"}]},"watch":{"broadcast":{"broadcasters":{"national":[],"canadian":[],"vTeam":[{"shortName":"FSSUN","longName":"Fox Sports Sun"}],"hTeam":[{"shortName":"FSSE-MEM","longName":"Fox Sports Southeast - Memphis"}],"spanish_hTeam":[],"spanish_vTeam":[],"spanish_national":[]},"video":{"regionalBlackoutCodes":"","canPurchase":true,"isLeaguePass":true,"isNationalBlackout":false,"isTNTOT":false,"isVR":false,"tntotIsOnAir":false,"isNextVR":false,"isNBAOnTNTVR":false,"isMagicLeap":false,"isOculusVenues":false,"streams":[{"streamType":"vTeam","isOnAir":false,"doesArchiveExist":true,"isArchiveAvailToWatch":true,"streamId":"100219003971220","duration":0},{"streamType":"hTeam","isOnAir":false,"doesArchiveExist":true,"isArchiveAvailToWatch":true,"streamId":"100219003971120","duration":0},{"streamType":"espanol_vTeam","isOnAir":false,"doesArchiveExist":false,"isArchiveAvailToWatch":false,"streamId":"","duration":0},{"streamType":"espanol_hTeam","isOnAir":false,"doesArchiveExist":false,"isArchiveAvailToWatch":false,"streamId":"","duration":0},{"streamType":"espanol_natl","isOnAir":false,"doesArchiveExist":false,"isArchiveAvailToWatch":false,"streamId":"","duration":0},{"streamType":"mobile","isOnAir":false,"doesArchiveExist":true,"isArchiveAvailToWatch":true,"streamId":"100219003971320","duration":0},{"streamType":"condensed","isOnAir":false,"doesArchiveExist":true,"isArchiveAvailToWatch":true,"streamId":"100219003971030","duration":0},{"streamType":"alt","isOnAir":false,"doesArchiveExist":false,"isArchiveAvailToWatch":false,"streamId":"","duration":0}],"deepLink":[]},"audio":{"national":{"streams":[{"language":"English","isOnAir":false,"streamId":""},{"language":"Spanish","isOnAir":false,"streamId":""}],"broadcasters":[]},"vTeam":{"streams":[{"language":"English","isOnAir":true,"streamId":"100219003972211"},{"language":"Spanish","isOnAir":true,"streamId":"100219003972212"}],"broadcasters":[{"shortName":"WAXY 790 AM / S: WAQI 710 AM","longName":"WAXY 790 AM / S: WAQI 710 AM"}]},"hTeam":{"streams":[{"language":"English","isOnAir":true,"streamId":"100219003972111"},{"language":"Spanish","isOnAir":false,"streamId":""}],"broadcasters":[{"shortName":"ESPN Radio 92.9FM / 680AM","longName":"ESPN Radio 92.9FM / 680AM"}]}}}}},{"seasonStageId":2,"seasonYear":"2019","leagueName":"standard","gameId":"0021900398","arena":{"name":"Fiserv Forum","isDomestic":true,"city":"Milwaukee","stateAbbr":"WI","country":"USA"},"isGameActivated":false,"statusNum":3,"extendedStatusNum":0,"startTimeEastern":"8:00 PM ET","startTimeUTC":"2019-12-17T01:00:00.000Z","endTimeUTC":"2019-12-17T03:38:00.000Z","startDateEastern":"20191216","homeStartDate":"20191216","homeStartTime":"1900","visitorStartDate":"20191216","visitorStartTime":"1900","gameUrlCode":"20191216/DALMIL","clock":"","isBuzzerBeater":false,"isPreviewArticleAvail":true,"isRecapArticleAvail":true,"nugget":{"text":"Porzingis: 26 pts, 12 reb | Giannis: 48 pts, 14 reb"},"attendance":"17727","tickets":{"mobileApp":"https://a.data.nba.com/tickets/single/2019/0021900398/APP_TIX","desktopWeb":"https://a.data.nba.com/tickets/single/2019/0021900398/TEAM_SCH","mobileWeb":"https://a.data.nba.com/tickets/single/2019/0021900398/WEB_MWEB","leagGameInfo":"https://a.data.nba.com/tickets/single/2019/0021900398/LEAG_GAMEINFO","leagTix":"https://a.data.nba.com/tickets/single/2019/0021900398/LEAG_TIX"},"hasGameBookPdf":true,"isStartTimeTBD":false,"gameDuration":{"hours":"2","minutes":"26"},"period":{"current":4,"type":0,"maxRegular":4,"isHalftime":false,"isEndOfPeriod":false},"vTeam":{"teamId":"1610612742","triCode":"DAL","win":"18","loss":"8","seriesWin":"1","seriesLoss":"0","score":"120","linescore":[{"score":"36"},{"score":"23"},{"score":"27"},{"score":"34"}]},"hTeam":{"teamId":"1610612749","triCode":"MIL","win":"24","loss":"4","seriesWin":"0","seriesLoss":"1","score":"116","linescore":[{"score":"22"},{"score":"34"},{"score":"20"},{"score":"40"}]},"watch":{"broadcast":{"broadcasters":{"national":[{"shortName":"NBA TV","longName":"NBA TV"}],"canadian":[{"shortName":"TSN","longName":"TSN"}],"vTeam":[{"shortName":"FSSW-DAL","longName":"Fox Sports Southwest - Dallas"}],"hTeam":[{"shortName":"FSWIS","longName":"Fox Sports Wisconsin"}],"spanish_hTeam":[],"spanish_vTeam":[],"spanish_national":[]},"video":{"regionalBlackoutCodes":"","canPurchase":true,"isLeaguePass":true,"isNationalBlackout":false,"isTNTOT":false,"isVR":false,"tntotIsOnAir":false,"isNextVR":false,"isNBAOnTNTVR":false,"isMagicLeap":false,"isOculusVenues":false,"streams":[{"streamType":"vTeam","isOnAir":false,"doesArchiveExist":true,"isArchiveAvailToWatch":true,"streamId":"100219003981220","duration":0},{"streamType":"hTeam","isOnAir":false,"doesArchiveExist":true,"isArchiveAvailToWatch":true,"streamId":"100219003981120","duration":0},{"streamType":"espanol_vTeam","isOnAir":false,"doesArchiveExist":false,"isArchiveAvailToWatch":false,"streamId":"","duration":0},{"streamType":"espanol_hTeam","isOnAir":false,"doesArchiveExist":false,"isArchiveAvailToWatch":false,"streamId":"","duration":0},{"streamType":"espanol_natl","isOnAir":false,"doesArchiveExist":false,"isArchiveAvailToWatch":false,"streamId":"","duration":0},{"streamType":"mobile","isOnAir":false,"doesArchiveExist":true,"isArchiveAvailToWatch":true,"streamId":"100219003981320","duration":0},{"streamType":"condensed","isOnAir":false,"doesArchiveExist":true,"isArchiveAvailToWatch":true,"streamId":"100219003981030","duration":0},{"streamType":"alt","isOnAir":false,"doesArchiveExist":false,"isArchiveAvailToWatch":false,"streamId":"","duration":0}],"deepLink":[]},"audio":{"national":{"streams":[{"language":"English","isOnAir":false,"streamId":""},{"language":"Spanish","isOnAir":false,"streamId":""}],"broadcasters":[]},"vTeam":{"streams":[{"language":"English","isOnAir":true,"streamId":"100219003982211"},{"language":"Spanish","isOnAir":true,"streamId":"100219003982212"}],"broadcasters":[{"shortName":"ESPN 103.3 FM / 1270 AM (ESP)","longName":"ESPN 103.3 FM / 1270 AM (ESP)"}]},"hTeam":{"streams":[{"language":"English","isOnAir":true,"streamId":"100219003982111"},{"language":"Spanish","isOnAir":false,"streamId":""}],"broadcasters":[{"shortName":"620 AM/103.3 FM WTMJ","longName":"620 AM/103.3 FM WTMJ"}]}}}}},{"seasonStageId":2,"seasonYear":"2019","leagueName":"standard","gameId":"0021900399","arena":{"name":"Chesapeake Energy Arena","isDomestic":true,"city":"Oklahoma City","stateAbbr":"OK","country":"USA"},"isGameActivated":false,"statusNum":3,"extendedStatusNum":0,"startTimeEastern":"8:00 PM ET","startTimeUTC":"2019-12-17T01:00:00.000Z","endTimeUTC":"2019-12-17T03:32:00.000Z","startDateEastern":"20191216","homeStartDate":"20191216","homeStartTime":"1900","visitorStartDate":"20191216","visitorStartTime":"1900","gameUrlCode":"20191216/CHIOKC","clock":"","isBuzzerBeater":false,"isPreviewArticleAvail":true,"isRecapArticleAvail":true,"nugget":{"text":"Paul: 30 pts | OKC: Overcomes 26-pt deficit "},"attendance":"18203","tickets":{"mobileApp":"https://a.data.nba.com/tickets/single/2019/0021900399/APP_TIX","desktopWeb":"https://a.data.nba.com/tickets/single/2019/0021900399/TEAM_SCH","mobileWeb":"https://a.data.nba.com/tickets/single/2019/0021900399/WEB_MWEB","leagGameInfo":"https://a.data.nba.com/tickets/single/2019/0021900399/LEAG_GAMEINFO","leagTix":"https://a.data.nba.com/tickets/single/2019/0021900399/LEAG_TIX"},"hasGameBookPdf":true,"isStartTimeTBD":false,"gameDuration":{"hours":"2","minutes":"20"},"period":{"current":4,"type":0,"maxRegular":4,"isHalftime":false,"isEndOfPeriod":false},"vTeam":{"teamId":"1610612741","triCode":"CHI","win":"10","loss":"19","seriesWin":"0","seriesLoss":"1","score":"106","linescore":[{"score":"37"},{"score":"31"},{"score":"22"},{"score":"16"}]},"hTeam":{"teamId":"1610612760","triCode":"OKC","win":"12","loss":"14","seriesWin":"1","seriesLoss":"0","score":"109","linescore":[{"score":"16"},{"score":"33"},{"score":"33"},{"score":"27"}]},"watch":{"broadcast":{"broadcasters":{"national":[],"canadian":[],"vTeam":[{"shortName":"NBCSCH","longName":"NBC Sports Chicago"}],"hTeam":[{"shortName":"FSOK","longName":"Fox Sports Oklahoma"}],"spanish_hTeam":[],"spanish_vTeam":[],"spanish_national":[]},"video":{"regionalBlackoutCodes":"","canPurchase":true,"isLeaguePass":true,"isNationalBlackout":false,"isTNTOT":false,"isVR":false,"tntotIsOnAir":false,"isNextVR":false,"isNBAOnTNTVR":false,"isMagicLeap":false,"isOculusVenues":false,"streams":[{"streamType":"vTeam","isOnAir":false,"doesArchiveExist":true,"isArchiveAvailToWatch":true,"streamId":"100219003991220","duration":0},{"streamType":"hTeam","isOnAir":false,"doesArchiveExist":true,"isArchiveAvailToWatch":true,"streamId":"100219003991120","duration":0},{"streamType":"espanol_vTeam","isOnAir":false,"doesArchiveExist":false,"isArchiveAvailToWatch":false,"streamId":"","duration":0},{"streamType":"espanol_hTeam","isOnAir":false,"doesArchiveExist":false,"isArchiveAvailToWatch":false,"streamId":"","duration":0},{"streamType":"espanol_natl","isOnAir":false,"doesArchiveExist":false,"isArchiveAvailToWatch":false,"streamId":"","duration":0},{"streamType":"mobile","isOnAir":false,"doesArchiveExist":true,"isArchiveAvailToWatch":true,"streamId":"100219003991320","duration":0},{"streamType":"condensed","isOnAir":false,"doesArchiveExist":true,"isArchiveAvailToWatch":true,"streamId":"100219003991030","duration":0},{"streamType":"alt","isOnAir":false,"doesArchiveExist":false,"isArchiveAvailToWatch":false,"streamId":"","duration":0}],"deepLink":[]},"audio":{"national":{"streams":[{"language":"English","isOnAir":false,"streamId":""},{"language":"Spanish","isOnAir":false,"streamId":""}],"broadcasters":[]},"vTeam":{"streams":[{"language":"English","isOnAir":true,"streamId":"100219003992211"},{"language":"Spanish","isOnAir":false,"streamId":""}],"broadcasters":[{"shortName":"WSCR-AM 670","longName":"WSCR-AM 670"}]},"hTeam":{"streams":[{"language":"English","isOnAir":true,"streamId":"100219003992111"},{"language":"Spanish","isOnAir":true,"streamId":"100219003992112"}],"broadcasters":[{"shortName":"WWLS 98.1FM OKC / 930AM (ESP)","longName":"WWLS 98.1FM OKC / 930AM (ESP)"}]}}}}},{"seasonStageId":2,"seasonYear":"2019","leagueName":"standard","gameId":"0021900400","arena":{"name":"Talking Stick Resort Arena","isDomestic":true,"city":"Phoenix","stateAbbr":"AZ","country":"USA"},"isGameActivated":false,"statusNum":3,"extendedStatusNum":0,"startTimeEastern":"9:00 PM ET","startTimeUTC":"2019-12-17T02:00:00.000Z","endTimeUTC":"2019-12-17T04:27:00.000Z","startDateEastern":"20191216","homeStartDate":"20191216","homeStartTime":"1900","visitorStartDate":"20191216","visitorStartTime":"1800","gameUrlCode":"20191216/PORPHX","clock":"","isBuzzerBeater":false,"isPreviewArticleAvail":true,"isRecapArticleAvail":true,"nugget":{"text":"McCollum: 30 points | Lillard: 27 points"},"attendance":"14193","tickets":{"mobileApp":"https://a.data.nba.com/tickets/single/2019/0021900400/APP_TIX","desktopWeb":"https://a.data.nba.com/tickets/single/2019/0021900400/TEAM_SCH","mobileWeb":"https://a.data.nba.com/tickets/single/2019/0021900400/WEB_MWEB","leagGameInfo":"https://a.data.nba.com/tickets/single/2019/0021900400/LEAG_GAMEINFO","leagTix":"https://a.data.nba.com/tickets/single/2019/0021900400/LEAG_TIX"},"hasGameBookPdf":true,"isStartTimeTBD":false,"gameDuration":{"hours":"2","minutes":"17"},"period":{"current":4,"type":0,"maxRegular":4,"isHalftime":false,"isEndOfPeriod":false},"vTeam":{"teamId":"1610612757","triCode":"POR","win":"11","loss":"16","seriesWin":"1","seriesLoss":"0","score":"111","linescore":[{"score":"25"},{"score":"34"},{"score":"31"},{"score":"21"}]},"hTeam":{"teamId":"1610612756","triCode":"PHX","win":"11","loss":"15","seriesWin":"0","seriesLoss":"1","score":"110","linescore":[{"score":"33"},{"score":"34"},{"score":"21"},{"score":"22"}]},"watch":{"broadcast":{"broadcasters":{"national":[],"canadian":[{"shortName":"NBAC","longName":"NBA TV Canada"}],"vTeam":[{"shortName":"NBCSNW","longName":"NBC SPORTS NORTHWEST"}],"hTeam":[{"shortName":"FSA","longName":"Fox Sports Arizona"}],"spanish_hTeam":[],"spanish_vTeam":[],"spanish_national":[]},"video":{"regionalBlackoutCodes":"","canPurchase":true,"isLeaguePass":true,"isNationalBlackout":false,"isTNTOT":false,"isVR":true,"tntotIsOnAir":false,"isNextVR":false,"isNBAOnTNTVR":false,"isMagicLeap":true,"isOculusVenues":false,"streams":[{"streamType":"vTeam","isOnAir":false,"doesArchiveExist":true,"isArchiveAvailToWatch":true,"streamId":"100219004001220","duration":0},{"streamType":"hTeam","isOnAir":false,"doesArchiveExist":true,"isArchiveAvailToWatch":true,"streamId":"100219004001120","duration":0},{"streamType":"espanol_vTeam","isOnAir":false,"doesArchiveExist":false,"isArchiveAvailToWatch":false,"streamId":"","duration":0},{"streamType":"espanol_hTeam","isOnAir":false,"doesArchiveExist":false,"isArchiveAvailToWatch":false,"streamId":"","duration":0},{"streamType":"espanol_natl","isOnAir":false,"doesArchiveExist":false,"isArchiveAvailToWatch":false,"streamId":"","duration":0},{"streamType":"mobile","isOnAir":false,"doesArchiveExist":true,"isArchiveAvailToWatch":true,"streamId":"100219004001320","duration":0},{"streamType":"condensed","isOnAir":false,"doesArchiveExist":true,"isArchiveAvailToWatch":true,"streamId":"100219004001030","duration":0},{"streamType":"alt","isOnAir":false,"doesArchiveExist":false,"isArchiveAvailToWatch":false,"streamId":"","duration":0}],"deepLink":[]},"audio":{"national":{"streams":[{"language":"English","isOnAir":false,"streamId":""},{"language":"Spanish","isOnAir":false,"streamId":""}],"broadcasters":[]},"vTeam":{"streams":[{"language":"English","isOnAir":true,"streamId":"100219004002211"},{"language":"Spanish","isOnAir":false,"streamId":""}],"broadcasters":[{"shortName":"Rip City Radio 620","longName":"Rip City Radio 620"}]},"hTeam":{"streams":[{"language":"English","isOnAir":true,"streamId":"100219004002111"},{"language":"Spanish","isOnAir":true,"streamId":"100219004002112"}],"broadcasters":[{"shortName":"AZ Sports 98.7 FM","longName":"AZ Sports 98.7 FM"}]}}}}}]}