{"_internal":{"pubDateTime":"2020-03-05 16:24:16.236 EST","igorPath":"S3,1583443442931,1583443450596|nbads,1583443450596,1583443451119|poller16,1583443455743,1583443455789|router,1583443455789,1583443455793|domUpdater,1583443455793,1583443456167|feedProducer,1583443456167,1583443456256","routeName":"boxscore","routeValue":"S3::2019_20200112/linescores/0021900590.xml","xslt":"NBA/xsl/date/scoreboard/marty_daily_scoreboard.xsl","xsltForceRecompile":"true","xsltInCache":"false","xsltCompileTimeMillis":"47","xsltTransformTimeMillis":"28","consolidatedDomKey":"prod__transform__marty_daily_scoreboard__7281118403769","endToEndTimeMillis":"13325"},"numGames":7,"games":[{"seasonStageId":2,"seasonYear":"2019","leagueName":"standard","gameId":"0021900584","arena":{"name":"Madison Square Garden","isDomestic":true,"city":"New York","stateAbbr":"NY","country":"USA"},"isGameActivated":false,"statusNum":3,"extendedStatusNum":0,"startTimeEastern":"3:30 PM ET","startTimeUTC":"2020-01-12T20:30:00.000Z","endTimeUTC":"2020-01-12T23:07:00.000Z","startDateEastern":"20200112","homeStartDate":"20200112","homeStartTime":"1530","visitorStartDate":"20200112","visitorStartTime":"1530","gameUrlCode":"20200112/MIANYK","clock":"","isBuzzerBeater":false,"isPreviewArticleAvail":true,"isRecapArticleAvail":true,"nugget":{"text":"Randle: 26 points | Barrett: 23 points (7-10 FGs)"},"attendance":"18861","tickets":{"mobileApp":"https://a.data.nba.com/tickets/single/2019/0021900584/APP_TIX","desktopWeb":"https://a.data.nba.com/tickets/single/2019/0021900584/TEAM_SCH","mobileWeb":"https://a.data.nba.com/tickets/single/2019/0021900584/WEB_MWEB","leagGameInfo":"https://a.data.nba.com/tickets/single/2019/0021900584/LEAG_GAMEINFO","leagTix":"https://a.data.nba.com/tickets/single/2019/0021900584/LEAG_TIX"},"hasGameBookPdf":true,"isStartTimeTBD":false,"gameDuration":{"hours":"2","minutes":"24"},"period":{"current":4,"type":0,"maxRegular":4,"isHalftime":false,"isEndOfPeriod":false},"vTeam":{"teamId":"1610612748","triCode":"MIA","win":"27","loss":"12","seriesWin":"1","seriesLoss":"1","score":"121","linescore":[{"score":"31"},{"score":"29"},{"score":"34"},{"score":"27"}]},"hTeam":{"teamId":"1610612752","triCode":"NYK","win":"11","loss":"29","seriesWin":"1","seriesLoss":"1","score":"124","linescore":[{"score":"27"},{"score":"28"},{"score":"29"},{"score":"40"}]},"watch":{"broadcast":{"broadcasters":{"national":[],"canadian":[{"shortName":"TSN2","longName":"TSN2"}],"vTeam":[{"shortName":"FSSUN","longName":"Fox Sports Sun"}],"hTeam":[{"shortName":"MSG","longName":"MSG"}],"spanish_hTeam":[],"spanish_vTeam":[],"spanish_national":[]},"video":{"regionalBlackoutCodes":"","canPurchase":true,"isLeaguePass":true,"isNationalBlackout":false,"isTNTOT":false,"isVR":false,"tntotIsOnAir":false,"isNextVR":false,"isNBAOnTNTVR":false,"isMagicLeap":false,"isOculusVenues":false,"streams":[{"streamType":"vTeam","isOnAir":false,"doesArchiveExist":true,"isArchiveAvailToWatch":true,"streamId":"100219005841220","duration":0},{"streamType":"hTeam","isOnAir":false,"doesArchiveExist":true,"isArchiveAvailToWatch":true,"streamId":"100219005841120","duration":0},{"streamType":"espanol_vTeam","isOnAir":false,"doesArchiveExist":false,"isArchiveAvailToWatch":false,"streamId":"","duration":0},{"streamType":"espanol_hTeam","isOnAir":false,"doesArchiveExist":false,"isArchiveAvailToWatch":false,"streamId":"","duration":0},{"streamType":"espanol_natl","isOnAir":false,"doesArchiveExist":false,"isArchiveAvailToWatch":false,"streamId":"","duration":0},{"streamType":"mobile","isOnAir":false,"doesArchiveExist":true,"isArchiveAvailToWatch":true,"streamId":"100219005841320","duration":0},{"streamType":"condensed","isOnAir":false,"doesArchiveExist":true,"isArchiveAvailToWatch":true,"streamId":"100219005841030","duration":0},{"streamType":"alt","isOnAir":false,"doesArchiveExist":false,"isArchiveAvailToWatch":false,"streamId":"","duration":0}],"deepLink":[{"broadcaster":"MSG","regionalMarketCodes":"nykr","iosApp":"http://www.msggo.com/","androidApp":"http://www.msggo.com/","desktopWeb":"http://www.msggo.com/","mobileWeb":"http://www.msggo.com/"}]},"audio":{"national":{"streams":[{"language":"English","isOnAir":false,"streamId":""},{"language":"Spanish","isOnAir":false,"streamId":""}],"broadcasters":[]},"vTeam":{"streams":[{"language":"English","isOnAir":false,"streamId":""},{"language":"Spanish","isOnAir":false,"streamId":""}],"broadcasters":[{"shortName":"WAXY 790 AM / S: WAQI 710 AM","longName":"WAXY 790 AM / S: WAQI 710 AM"}]},"hTeam":{"streams":[{"language":"English","isOnAir":false,"streamId":""},{"language":"Spanish","isOnAir":false,"streamId":""}],"broadcasters":[{"shortName":"ESPN NY 98.7","longName":"ESPN NY 98.7"}]}}}}},{"seasonStageId":2,"seasonYear":"2019","leagueName":"standard","gameId":"0021900585","arena":{"name":"Capital One Arena","isDomestic":true,"city":"Washington","stateAbbr":"DC","country":"USA"},"isGameActivated":false,"statusNum":3,"extendedStatusNum":0,"startTimeEastern":"3:30 PM ET","startTimeUTC":"2020-01-12T20:30:00.000Z","endTimeUTC":"2020-01-12T23:01:00.000Z","startDateEastern":"20200112","homeStartDate":"20200112","homeStartTime":"1530","visitorStartDate":"20200112","visitorStartTime":"1330","gameUrlCode":"20200112/UTAWAS","clock":"","isBuzzerBeater":false,"isPreviewArticleAvail":true,"isRecapArticleAvail":true,"nugget":{"text":"Bogdanovic: 31 points | Gobert: 21 pts, 14 reb"},"attendance":"15953","tickets":{"mobileApp":"https://a.data.nba.com/tickets/single/2019/0021900585/APP_TIX","desktopWeb":"https://a.data.nba.com/tickets/single/2019/0021900585/TEAM_SCH","mobileWeb":"https://a.data.nba.com/tickets/single/2019/0021900585/WEB_MWEB","leagGameInfo":"https://a.data.nba.com/tickets/single/2019/0021900585/LEAG_GAMEINFO","leagTix":"https://a.data.nba.com/tickets/single/2019/0021900585/LEAG_TIX"},"hasGameBookPdf":true,"isStartTimeTBD":false,"gameDuration":{"hours":"2","minutes":"13"},"period":{"current":4,"type":0,"maxRegular":4,"isHalftime":false,"isEndOfPeriod":false},"vTeam":{"teamId":"1610612762","triCode":"UTA","win":"27","loss":"12","seriesWin":"1","seriesLoss":"0","score":"127","linescore":[{"score":"23"},{"score":"32"},{"score":"38"},{"score":"34"}]},"hTeam":{"teamId":"1610612764","triCode":"WAS","win":"13","loss":"26","seriesWin":"0","seriesLoss":"1","score":"116","linescore":[{"score":"34"},{"score":"32"},{"score":"25"},{"score":"25"}]},"watch":{"broadcast":{"broadcasters":{"national":[],"canadian":[],"vTeam":[{"shortName":"ATTSN-RM","longName":"AT&T Sportsnet - Rocky Mountain"}],"hTeam":[{"shortName":"NBCSWA","longName":"NBC SPORTS WASHINGTON"}],"spanish_hTeam":[],"spanish_vTeam":[],"spanish_national":[]},"video":{"regionalBlackoutCodes":"","canPurchase":true,"isLeaguePass":true,"isNationalBlackout":false,"isTNTOT":false,"isVR":false,"tntotIsOnAir":false,"isNextVR":false,"isNBAOnTNTVR":false,"isMagicLeap":false,"isOculusVenues":false,"streams":[{"streamType":"vTeam","isOnAir":false,"doesArchiveExist":true,"isArchiveAvailToWatch":true,"streamId":"100219005851220","duration":0},{"streamType":"hTeam","isOnAir":false,"doesArchiveExist":true,"isArchiveAvailToWatch":true,"streamId":"100219005851120","duration":0},{"streamType":"espanol_vTeam","isOnAir":false,"doesArchiveExist":false,"isArchiveAvailToWatch":false,"streamId":"","duration":0},{"streamType":"espanol_hTeam","isOnAir":false,"doesArchiveExist":false,"isArchiveAvailToWatch":false,"streamId":"","duration":0},{"streamType":"espanol_natl","isOnAir":false,"doesArchiveExist":false,"isArchiveAvailToWatch":false,"streamId":"","duration":0},{"streamType":"mobile","isOnAir":false,"doesArchiveExist":true,"isArchiveAvailToWatch":true,"streamId":"100219005851320","duration":0},{"streamType":"condensed","isOnAir":false,"doesArchiveExist":true,"isArchiveAvailToWatch":true,"streamId":"100219005851030","duration":0},{"streamType":"alt","isOnAir":false,"doesArchiveExist":false,"isArchiveAvailToWatch":false,"streamId":"","duration":0}],"deepLink":[]},"audio":{"national":{"streams":[{"language":"English","isOnAir":false,"streamId":""},{"language":"Spanish","isOnAir":false,"streamId":""}],"broadcasters":[]},"vTeam":{"streams":[{"language":"English","isOnAir":false,"streamId":""},{"language":"Spanish","isOnAir":false,"streamId":""}],"broadcasters":[{"shortName":"97.5 FM | 1280 AM The Zone","longName":"97.5 FM | 1280 AM The Zone"}]},"hTeam":{"streams":[{"language":"English","isOnAir":false,"streamId":""},{"language":"Spanish","isOnAir":false,"streamId":""}],"broadcasters":[{"shortName":"1500 AM","longName":"1500 AM"}]}}}}},{"seasonStageId":2,"seasonYear":"2019","leagueName":"standard","gameId":"0021900586","arena":{"name":"Barclays Center","isDomestic":true,"city":"Brooklyn","stateAbbr":"NY","country":"USA"},"isGameActivated":false,"statusNum":3,"extendedStatusNum":0,"startTimeEastern":"6:00 PM ET","startTimeUTC":"2020-01-12T23:00:00.000Z","endTimeUTC":"2020-01-13T01:21:00.000Z","startDateEastern":"20200112","homeStartDate":"20200112","homeStartTime":"1800","visitorStartDate":"20200112","visitorStartTime":"1800","gameUrlCode":"20200112/ATLBKN","clock":"","isBuzzerBeater":false,"isPreviewArticleAvail":true,"isRecapArticleAvail":true,"nugget":{"text":"Irving: 21 points (10-11 FGs) | Reddish: 20 pts"},"attendance":"15201","tickets":{"mobileApp":"https://a.data.nba.com/tickets/single/2019/0021900586/APP_TIX","desktopWeb":"https://a.data.nba.com/tickets/single/2019/0021900586/TEAM_SCH","mobileWeb":"https://a.data.nba.com/tickets/single/2019/0021900586/WEB_MWEB","leagGameInfo":"https://a.data.nba.com/tickets/single/2019/0021900586/LEAG_GAMEINFO","leagTix":"https://a.data.nba.com/tickets/single/2019/0021900586/LEAG_TIX"},"hasGameBookPdf":true,"isStartTimeTBD":false,"gameDuration":{"hours":"2","minutes":"10"},"period":{"current":4,"type":0,"maxRegular":4,"isHalftime":false,"isEndOfPeriod":false},"vTeam":{"teamId":"1610612737","triCode":"ATL","win":"8","loss":"32","seriesWin":"0","seriesLoss":"3","score":"86","linescore":[{"score":"16"},{"score":"30"},{"score":"20"},{"score":"20"}]},"hTeam":{"teamId":"1610612751","triCode":"BKN","win":"18","loss":"20","seriesWin":"3","seriesLoss":"0","score":"108","linescore":[{"score":"37"},{"score":"33"},{"score":"22"},{"score":"16"}]},"watch":{"broadcast":{"broadcasters":{"national":[],"canadian":[],"vTeam":[{"shortName":"FSSE-ATL","longName":"Fox Sports Southeast - Atlanta"}],"hTeam":[{"shortName":"YES","longName":"YES Network"}],"spanish_hTeam":[],"spanish_vTeam":[],"spanish_national":[]},"video":{"regionalBlackoutCodes":"","canPurchase":true,"isLeaguePass":true,"isNationalBlackout":false,"isTNTOT":false,"isVR":false,"tntotIsOnAir":false,"isNextVR":false,"isNBAOnTNTVR":false,"isMagicLeap":false,"isOculusVenues":false,"streams":[{"streamType":"vTeam","isOnAir":false,"doesArchiveExist":true,"isArchiveAvailToWatch":true,"streamId":"100219005861220","duration":0},{"streamType":"hTeam","isOnAir":false,"doesArchiveExist":true,"isArchiveAvailToWatch":true,"streamId":"100219005861120","duration":0},{"streamType":"espanol_vTeam","isOnAir":false,"doesArchiveExist":false,"isArchiveAvailToWatch":false,"streamId":"","duration":0},{"streamType":"espanol_hTeam","isOnAir":false,"doesArchiveExist":false,"isArchiveAvailToWatch":false,"streamId":"","duration":0},{"streamType":"espanol_natl","isOnAir":false,"doesArchiveExist":false,"isArchiveAvailToWatch":false,"streamId":"","duration":0},{"streamType":"mobile","isOnAir":false,"doesArchiveExist":true,"isArchiveAvailToWatch":true,"streamId":"100219005861320","duration":0},{"streamType":"condensed","isOnAir":false,"doesArchiveExist":true,"isArchiveAvailToWatch":true,"streamId":"100219005861030","duration":0},{"streamType":"alt","isOnAir":false,"doesArchiveExist":false,"isArchiveAvailToWatch":false,"streamId":"","duration":0}],"deepLink":[]},"audio":{"national":{"streams":[{"language":"English","isOnAir":false,"streamId":""},{"language":"Spanish","isOnAir":false,"streamId":""}],"broadcasters":[]},"vTeam":{"streams":[{"language":"English","isOnAir":false,"streamId":""},{"language":"Spanish","isOnAir":false,"streamId":""}],"broadcasters":[{"shortName":"WZGC 92.9 FM The Game","longName":"WZGC 92.9 FM The Game"}]},"hTeam":{"streams":[{"language":"English","isOnAir":false,"streamId":""},{"language":"Spanish","isOnAir":false,"streamId":""}],"broadcasters":[{"shortName":"WCBS 880 AM","longName":"WCBS 880 AM"}]}}}}},{"seasonStageId":2,"seasonYear":"2019","leagueName":"standard","gameId":"0021900587","arena":{"name":"Scotiabank Arena","isDomestic":false,"city":"Toronto","stateAbbr":"ON","country":"Canada"},"isGameActivated":false,"statusNum":3,"extendedStatusNum":0,"startTimeEastern":"6:00 PM ET","startTimeUTC":"2020-01-12T23:00:00.000Z","endTimeUTC":"2020-01-13T01:25:00.000Z","startDateEastern":"20200112","homeStartDate":"20200112","homeStartTime":"1800","visitorStartDate":"20200112","visitorStartTime":"1700","gameUrlCode":"20200112/SASTOR","clock":"","isBuzzerBeater":false,"isPreviewArticleAvail":true,"isRecapArticleAvail":true,"nugget":{"text":"DeRozan: 25 points | Ibaka: 21 points, 14 rebounds"},"attendance":"19800","tickets":{"mobileApp":"https://a.data.nba.com/tickets/single/2019/0021900587/APP_TIX","desktopWeb":"https://a.data.nba.com/tickets/single/2019/0021900587/TEAM_SCH","mobileWeb":"https://a.data.nba.com/tickets/single/2019/0021900587/WEB_MWEB","leagGameInfo":"https://a.data.nba.com/tickets/single/2019/0021900587/LEAG_GAMEINFO","leagTix":"https://a.data.nba.com/tickets/single/2019/0021900587/LEAG_TIX"},"hasGameBookPdf":true,"isStartTimeTBD":false,"gameDuration":{"hours":"2","minutes":"14"},"period":{"current":4,"type":0,"maxRegular":4,"isHalftime":false,"isEndOfPeriod":false},"vTeam":{"teamId":"1610612759","triCode":"SAS","win":"17","loss":"21","seriesWin":"1","seriesLoss":"0","score":"105","linescore":[{"score":"21"},{"score":"22"},{"score":"26"},{"score":"36"}]},"hTeam":{"teamId":"1610612761","triCode":"TOR","win":"25","loss":"14","seriesWin":"0","seriesLoss":"1","score":"104","linescore":[{"score":"28"},{"score":"23"},{"score":"31"},{"score":"22"}]},"watch":{"broadcast":{"broadcasters":{"national":[],"canadian":[{"shortName":"SN1","longName":"SN1"}],"vTeam":[{"shortName":"FSSW-SA","longName":"Fox Sports Southwest - San Antonio"}],"hTeam":[{"shortName":"SN1","longName":"SN1"}],"spanish_hTeam":[],"spanish_vTeam":[],"spanish_national":[]},"video":{"regionalBlackoutCodes":"","canPurchase":true,"isLeaguePass":true,"isNationalBlackout":false,"isTNTOT":false,"isVR":false,"tntotIsOnAir":false,"isNextVR":false,"isNBAOnTNTVR":false,"isMagicLeap":false,"isOculusVenues":false,"streams":[{"streamType":"vTeam","isOnAir":false,"doesArchiveExist":true,"isArchiveAvailToWatch":true,"streamId":"100219005871220","duration":0},{"streamType":"hTeam","isOnAir":false,"doesArchiveExist":true,"isArchiveAvailToWatch":true,"streamId":"100219005871120","duration":0},{"streamType":"espanol_vTeam","isOnAir":false,"doesArchiveExist":false,"isArchiveAvailToWatch":false,"streamId":"","duration":0},{"streamType":"espanol_hTeam","isOnAir":false,"doesArchiveExist":false,"isArchiveAvailToWatch":false,"streamId":"","duration":0},{"streamType":"espanol_natl","isOnAir":false,"doesArchiveExist":false,"isArchiveAvailToWatch":false,"streamId":"","duration":0},{"streamType":"mobile","isOnAir":false,"doesArchiveExist":true,"isArchiveAvailToWatch":true,"streamId":"100219005871320","duration":0},{"streamType":"condensed","isOnAir":false,"doesArchiveExist":true,"isArchiveAvailToWatch":true,"streamId":"100219005871030","duration":0},{"streamType":"alt","isOnAir":false,"doesArchiveExist":false,"isArchiveAvailToWatch":false,"streamId":"","duration":0}],"deepLink":[]},"audio":{"national":{"streams":[{"language":"English","isOnAir":false,"streamId":""},{"language":"Spanish","isOnAir":false,"streamId":""}],"broadcasters":[]},"vTeam":{"streams":[{"language":"English","isOnAir":false,"streamId":""},{"language":"Spanish","isOnAir":false,"streamId":""}],"broadcasters":[{"shortName":"WOAI 1200AM | S: KTXN 1350AM / 107.5FM H","longName":"WOAI 1200AM | S: KTXN 1350AM / 107.5FM H"}]},"hTeam":{"streams":[{"language":"English","isOnAir":false,"streamId":""},{"language":"Spanish","isOnAir":false,"streamId":""}],"broadcasters":[{"shortName":"Sportsnet 590 The FAN","longName":"Sportsnet 590 The FAN"}]}}}}},{"seasonStageId":2,"seasonYear":"2019","leagueName":"standard","gameId":"0021900588","arena":{"name":"FedExForum","isDomestic":true,"city":"Memphis","stateAbbr":"TN","country":"USA"},"isGameActivated":false,"statusNum":3,"extendedStatusNum":0,"startTimeEastern":"6:00 PM ET","startTimeUTC":"2020-01-12T23:00:00.000Z","endTimeUTC":"2020-01-13T01:12:00.000Z","startDateEastern":"20200112","homeStartDate":"20200112","homeStartTime":"1700","visitorStartDate":"20200112","visitorStartTime":"1500","gameUrlCode":"20200112/GSWMEM","clock":"","isBuzzerBeater":false,"isPreviewArticleAvail":true,"isRecapArticleAvail":true,"nugget":{"text":"Valanciunas: 31 pts, 19 reb | Russell: 34 points"},"attendance":"16408","tickets":{"mobileApp":"https://a.data.nba.com/tickets/single/2019/0021900588/APP_TIX","desktopWeb":"https://a.data.nba.com/tickets/single/2019/0021900588/TEAM_SCH","mobileWeb":"https://a.data.nba.com/tickets/single/2019/0021900588/WEB_MWEB","leagGameInfo":"https://a.data.nba.com/tickets/single/2019/0021900588/LEAG_GAMEINFO","leagTix":"https://a.data.nba.com/tickets/single/2019/0021900588/LEAG_TIX"},"hasGameBookPdf":true,"isStartTimeTBD":false,"gameDuration":{"hours":"2","minutes":"02"},"period":{"current":4,"type":0,"maxRegular":4,"isHalftime":false,"isEndOfPeriod":false},"vTeam":{"teamId":"1610612744","triCode":"GSW","win":"9","loss":"32","seriesWin":"1","seriesLoss":"2","score":"102","linescore":[{"score":"26"},{"score":"33"},{"score":"17"},{"score":"26"}]},"hTeam":{"teamId":"1610612763","triCode":"MEM","win":"18","loss":"22","seriesWin":"2","seriesLoss":"1","score":"122","linescore":[{"score":"27"},{"score":"33"},{"score":"35"},{"score":"27"}]},"watch":{"broadcast":{"broadcasters":{"national":[],"canadian":[],"vTeam":[{"shortName":"NBCSBA","longName":"NBC Sports  Bay Area"}],"hTeam":[{"shortName":"FSSE-MEM","longName":"Fox Sports Southeast - Memphis"}],"spanish_hTeam":[],"spanish_vTeam":[],"spanish_national":[]},"video":{"regionalBlackoutCodes":"","canPurchase":true,"isLeaguePass":true,"isNationalBlackout":false,"isTNTOT":false,"isVR":false,"tntotIsOnAir":false,"isNextVR":false,"isNBAOnTNTVR":false,"isMagicLeap":false,"isOculusVenues":false,"streams":[{"streamType":"vTeam","isOnAir":false,"doesArchiveExist":true,"isArchiveAvailToWatch":true,"streamId":"100219005881220","duration":0},{"streamType":"hTeam","isOnAir":false,"doesArchiveExist":true,"isArchiveAvailToWatch":true,"streamId":"100219005881120","duration":0},{"streamType":"espanol_vTeam","isOnAir":false,"doesArchiveExist":false,"isArchiveAvailToWatch":false,"streamId":"","duration":0},{"streamType":"espanol_hTeam","isOnAir":false,"doesArchiveExist":false,"isArchiveAvailToWatch":false,"streamId":"","duration":0},{"streamType":"espanol_natl","isOnAir":false,"doesArchiveExist":false,"isArchiveAvailToWatch":false,"streamId":"","duration":0},{"streamType":"mobile","isOnAir":false,"doesArchiveExist":true,"isArchiveAvailToWatch":true,"streamId":"100219005881320","duration":0},{"streamType":"condensed","isOnAir":false,"doesArchiveExist":true,"isArchiveAvailToWatch":true,"streamId":"100219005881030","duration":0},{"streamType":"alt","isOnAir":false,"doesArchiveExist":false,"isArchiveAvailToWatch":false,"streamId":"","duration":0}],"deepLink":[]},"audio":{"national":{"streams":[{"language":"English","isOnAir":false,"streamId":""},{"language":"Spanish","isOnAir":false,"streamId":""}],"broadcasters":[]},"vTeam":{"streams":[{"language":"English","isOnAir":false,"streamId":""},{"language":"Spanish","isOnAir":false,"streamId":""}],"broadcasters":[{"shortName":"95.7 The Game","longName":"95.7 The Game"}]},"hTeam":{"streams":[{"language":"English","isOnAir":false,"streamId":""},{"language":"Spanish","isOnAir":false,"streamId":""}],"broadcasters":[{"shortName":"ESPN Radio 92.9FM / 680AM","longName":"ESPN Radio 92.9FM / 680AM"}]}}}}},{"seasonStageId":2,"seasonYear":"2019","leagueName":"standard","gameId":"0021900589","arena":{"name":"Pepsi Center","isDomestic":true,"city":"Denver","stateAbbr":"CO","country":"USA"},"isGameActivated":false,"statusNum":3,"extendedStatusNum":0,"startTimeEastern":"8:00 PM ET","startTimeUTC":"2020-01-13T01:00:00.000Z","endTimeUTC":"2020-01-13T03:32:00.000Z","startDateEastern":"20200112","homeStartDate":"20200112","homeStartTime":"1800","visitorStartDate":"20200112","visitorStartTime":"1700","gameUrlCode":"20200112/LACDEN","clock":"","isBuzzerBeater":false,"isPreviewArticleAvail":true,"isRecapArticleAvail":true,"nugget":{"text":"Jokic: 20 points, 15 rebounds | Leonard: 30 pts"},"attendance":"19520","tickets":{"mobileApp":"https://a.data.nba.com/tickets/single/2019/0021900589/APP_TIX","desktopWeb":"https://a.data.nba.com/tickets/single/2019/0021900589/TEAM_SCH","mobileWeb":"https://a.data.nba.com/tickets/single/2019/0021900589/WEB_MWEB","leagGameInfo":"https://a.data.nba.com/tickets/single/2019/0021900589/LEAG_GAMEINFO","leagTix":"https://a.data.nba.com/tickets/single/2019/0021900589/LEAG_TIX"},"hasGameBookPdf":true,"isStartTimeTBD":false,"gameDuration":{"hours":"2","minutes":"21"},"period":{"current":4,"type":0,"maxRegular":4,"isHalftime":false,"isEndOfPeriod":false},"vTeam":{"teamId":"1610612746","triCode":"LAC","win":"27","loss":"13","seriesWin":"0","seriesLoss":"1","score":"104","linescore":[{"score":"30"},{"score":"22"},{"score":"22"},{"score":"30"}]},"hTeam":{"teamId":"1610612743","triCode":"DEN","win":"27","loss":"12","seriesWin":"1","seriesLoss":"0","score":"114","linescore":[{"score":"29"},{"score":"37"},{"score":"23"},{"score":"25"}]},"watch":{"broadcast":{"broadcasters":{"national":[],"canadian":[{"shortName":"TSN2","longName":"TSN2"}],"vTeam":[{"shortName":"FSPT","longName":"Fox Sports Prime Ticket"}],"hTeam":[{"shortName":"ALT","longName":"Altitude"}],"spanish_hTeam":[],"spanish_vTeam":[],"spanish_national":[]},"video":{"regionalBlackoutCodes":"","canPurchase":true,"isLeaguePass":true,"isNationalBlackout":false,"isTNTOT":false,"isVR":false,"tntotIsOnAir":false,"isNextVR":false,"isNBAOnTNTVR":false,"isMagicLeap":false,"isOculusVenues":false,"streams":[{"streamType":"vTeam","isOnAir":false,"doesArchiveExist":true,"isArchiveAvailToWatch":true,"streamId":"100219005891220","duration":0},{"streamType":"hTeam","isOnAir":false,"doesArchiveExist":true,"isArchiveAvailToWatch":true,"streamId":"100219005891120","duration":0},{"streamType":"espanol_vTeam","isOnAir":false,"doesArchiveExist":false,"isArchiveAvailToWatch":false,"streamId":"","duration":0},{"streamType":"espanol_hTeam","isOnAir":false,"doesArchiveExist":false,"isArchiveAvailToWatch":false,"streamId":"","duration":0},{"streamType":"espanol_natl","isOnAir":false,"doesArchiveExist":false,"isArchiveAvailToWatch":false,"streamId":"","duration":0},{"streamType":"mobile","isOnAir":false,"doesArchiveExist":true,"isArchiveAvailToWatch":true,"streamId":"100219005891320","duration":0},{"streamType":"condensed","isOnAir":false,"doesArchiveExist":true,"isArchiveAvailToWatch":true,"streamId":"100219005891030","duration":0},{"streamType":"alt","isOnAir":false,"doesArchiveExist":false,"isArchiveAvailToWatch":false,"streamId":"","duration":0}],"deepLink":[]},"audio":{"national":{"streams":[{"language":"English","isOnAir":false,"streamId":""},{"language":"Spanish","isOnAir":false,"streamId":""}],"broadcasters":[]},"vTeam":{"streams":[{"language":"English","isOnAir":false,"streamId":""},{"language":"Spanish","isOnAir":false,"streamId":""}],"broadcasters":[{"shortName":"AM 570 LA Sports","longName":"AM 570 LA Sports"}]},"hTeam":{"streams":[{"language":"English","isOnAir":false,"streamId":""},{"language":"Spanish","isOnAir":false,"streamId":""}],"broadcasters":[{"shortName":"KKSE 92.5FM/950AM","longName":"KKSE 92.5FM/950AM"}]}}}}},{"seasonStageId":2,"seasonYear":"2019","leagueName":"standard","gameId":"0021900590","arena":{"name":"Talking Stick Resort Arena","isDomestic":true,"city":"Phoenix","stateAbbr":"AZ","country":"USA"},"isGameActivated":false,"statusNum":3,"extendedStatusNum":0,"startTimeEastern":"8:00 PM ET","startTimeUTC":"2020-01-13T01:00:00.000Z","endTimeUTC":"2020-01-13T03:17:00.000Z","startDateEastern":"20200112","homeStartDate":"20200112","homeStartTime":"1800","visitorStartDate":"20200112","visitorStartTime":"2000","gameUrlCode":"20200112/CHAPHX","clock":"","isBuzzerBeater":false,"isPreviewArticleAvail":true,"isRecapArticleAvail":true,"nugget":{"text":"Oubre: 25 points, 15 rebounds | Bacon: 24 points"},"attendance":"14751","tickets":{"mobileApp":"https://a.data.nba.com/tickets/single/2019/0021900590/APP_TIX","desktopWeb":"https://a.data.nba.com/tickets/single/2019/0021900590/TEAM_SCH","mobileWeb":"https://a.data.nba.com/tickets/single/2019/0021900590/WEB_MWEB","leagGameInfo":"https://a.data.nba.com/tickets/single/2019/0021900590/LEAG_GAMEINFO","leagTix":"https://a.data.nba.com/tickets/single/2019/0021900590/LEAG_TIX"},"hasGameBookPdf":true,"isStartTimeTBD":false,"gameDuration":{"hours":"2","minutes":"07"},"period":{"current":4,"type":0,"maxRegular":4,"isHalftime":false,"isEndOfPeriod":false},"vTeam":{"teamId":"1610612766","triCode":"CHA","win":"15","loss":"27","seriesWin":"0","seriesLoss":"2","score":"92","linescore":[{"score":"24"},{"score":"21"},{"score":"26"},{"score":"21"}]},"hTeam":{"teamId":"1610612756","triCode":"PHX","win":"16","loss":"23","seriesWin":"2","seriesLoss":"0","score":"100","linescore":[{"score":"18"},{"score":"28"},{"score":"25"},{"score":"29"}]},"watch":{"broadcast":{"broadcasters":{"national":[],"canadian":[{"shortName":"NBAC","longName":"NBA TV Canada"}],"vTeam":[{"shortName":"FSSE-CHA","longName":"Fox Sports Southeast - Charlotte"}],"hTeam":[{"shortName":"FSA","longName":"Fox Sports Arizona"}],"spanish_hTeam":[],"spanish_vTeam":[],"spanish_national":[]},"video":{"regionalBlackoutCodes":"","canPurchase":true,"isLeaguePass":true,"isNationalBlackout":false,"isTNTOT":false,"isVR":false,"tntotIsOnAir":false,"isNextVR":false,"isNBAOnTNTVR":false,"isMagicLeap":false,"isOculusVenues":false,"streams":[{"streamType":"vTeam","isOnAir":false,"doesArchiveExist":true,"isArchiveAvailToWatch":true,"streamId":"100219005901220","duration":0},{"streamType":"hTeam","isOnAir":false,"doesArchiveExist":true,"isArchiveAvailToWatch":true,"streamId":"100219005901120","duration":0},{"streamType":"espanol_vTeam","isOnAir":false,"doesArchiveExist":false,"isArchiveAvailToWatch":false,"streamId":"","duration":0},{"streamType":"espanol_hTeam","isOnAir":false,"doesArchiveExist":false,"isArchiveAvailToWatch":false,"streamId":"","duration":0},{"streamType":"espanol_natl","isOnAir":false,"doesArchiveExist":false,"isArchiveAvailToWatch":false,"streamId":"","duration":0},{"streamType":"mobile","isOnAir":false,"doesArchiveExist":true,"isArchiveAvailToWatch":true,"streamId":"100219005901320","duration":0},{"streamType":"condensed","isOnAir":false,"doesArchiveExist":true,"isArchiveAvailToWatch":true,"streamId":"100219005901030","duration":0},{"streamType":"alt","isOnAir":false,"doesArchiveExist":false,"isArchiveAvailToWatch":false,"streamId":"","duration":0}],"deepLink":[]},"audio":{"national":{"streams":[{"language":"English","isOnAir":false,"streamId":""},{"language":"Spanish","isOnAir":false,"streamId":""}],"broadcasters":[]},"vTeam":{"streams":[{"language":"English","isOnAir":false,"streamId":""},{"language":"Spanish","isOnAir":false,"streamId":""}],"broadcasters":[{"shortName":"WFNZ 610 AM/102.5 FM","longName":"WFNZ 610 AM/102.5 FM"}]},"hTeam":{"streams":[{"language":"English","isOnAir":false,"streamId":""},{"language":"Spanish","isOnAir":false,"streamId":""}],"broadcasters":[{"shortName":"AZ Sports 98.7 FM","longName":"AZ Sports 98.7 FM"}]}}}}}]}