{"_internal":{"pubDateTime":"2020-03-22 06:00:31.118 EDT","igorPath":"cron,1584871225686,1584871225686|router,1584871225686,1584871225861|domUpdater,1584871226020,1584871230356|feedProducer,1584871230470,1584871231844","routeName":"CronJob::0600","routeValue":"CronJob::0600","xslt":"NBA/xsl/date/scoreboard/marty_daily_scoreboard.xsl","xsltForceRecompile":"true","xsltInCache":"false","xsltCompileTimeMillis":"607","xsltTransformTimeMillis":"99","consolidatedDomKey":"prod__transform__marty_daily_scoreboard__6460884769880","endToEndTimeMillis":"6158"},"numGames":5,"games":[{"seasonStageId":2,"seasonYear":"2019","leagueName":"standard","gameId":"0021901048","arena":{"name":"Little Caesars Arena","isDomestic":true,"city":"Detroit","stateAbbr":"MI","country":"USA"},"isGameActivated":false,"statusNum":1,"extendedStatusNum":0,"startTimeEastern":"","startTimeUTC":"2020-03-22","startDateEastern":"20200322","homeStartDate":"20200322","homeStartTime":"","visitorStartDate":"20200322","visitorStartTime":"","gameUrlCode":"20200322/LALDET","clock":"","isBuzzerBeater":false,"isPreviewArticleAvail":false,"isRecapArticleAvail":false,"nugget":{"text":""},"attendance":"","tickets":{"mobileApp":"https://a.data.nba.com/tickets/single/2019/0021901048/APP_TIX","desktopWeb":"https://a.data.nba.com/tickets/single/2019/0021901048/TEAM_SCH","mobileWeb":"https://a.data.nba.com/tickets/single/2019/0021901048/WEB_MWEB","leagGameInfo":"https://a.data.nba.com/tickets/single/2019/0021901048/LEAG_GAMEINFO","leagTix":"https://a.data.nba.com/tickets/single/2019/0021901048/LEAG_TIX"},"hasGameBookPdf":false,"isStartTimeTBD":true,"gameDuration":{"hours":"","minutes":""},"period":{"current":0,"type":0,"maxRegular":4,"isHalftime":false,"isEndOfPeriod":false},"vTeam":{"teamId":"1610612747","triCode":"LAL","win":"49","loss":"14","seriesWin":"1","seriesLoss":"0","score":"","linescore":[]},"hTeam":{"teamId":"1610612765","triCode":"DET","win":"20","loss":"46","seriesWin":"0","seriesLoss":"1","score":"","linescore":[]},"watch":{"broadcast":{"broadcasters":{"national":[],"canadian":[{"shortName":"TSN.CA/App","longName":"TSN.ca & TSN App"}],"vTeam":[{"shortName":"SPECSN","longName":"Spectrum SportsNet"}],"hTeam":[{"shortName":"FSD","longName":"Fox Sports Detroit"}],"spanish_hTeam":[],"spanish_vTeam":[],"spanish_national":[]},"video":{"regionalBlackoutCodes":"detr_lalr","canPurchase":false,"isLeaguePass":false,"isNationalBlackout":false,"isTNTOT":false,"isVR":true,"tntotIsOnAir":false,"isNextVR":false,"isNBAOnTNTVR":false,"isMagicLeap":true,"isOculusVenues":false,"streams":[{"streamType":"vTeam","isOnAir":false,"doesArchiveExist":false,"isArchiveAvailToWatch":false,"streamId":"","duration":0},{"streamType":"hTeam","isOnAir":false,"doesArchiveExist":false,"isArchiveAvailToWatch":false,"streamId":"","duration":0},{"streamType":"espanol_vTeam","isOnAir":false,"doesArchiveExist":false,"isArchiveAvailToWatch":false,"streamId":"","duration":0},{"streamType":"espanol_hTeam","isOnAir":false,"doesArchiveExist":false,"isArchiveAvailToWatch":false,"streamId":"","duration":0},{"streamType":"espanol_natl","isOnAir":false,"doesArchiveExist":false,"isArchiveAvailToWatch":false,"streamId":"","duration":0},{"streamType":"mobile","isOnAir":false,"doesArchiveExist":false,"isArchiveAvailToWatch":false,"streamId":"","duration":0},{"streamType":"condensed","isOnAir":false,"doesArchiveExist":false,"isArchiveAvailToWatch":false,"streamId":"","duration":0},{"streamType":"alt","isOnAir":false,"doesArchiveExist":false,"isArchiveAvailToWatch":false,"streamId":"","duration":0}],"deepLink":[]},"audio":{"national":{"streams":[{"language":"English","isOnAir":false,"streamId":""},{"language":"Spanish","isOnAir":false,"streamId":""}],"broadcasters":[]},"vTeam":{"streams":[{"language":"English","isOnAir":false,"streamId":""},{"language":"Spanish","isOnAir":false,"streamId":""}],"broadcasters":[{"shortName":"710 AM ESPN / 1330 AM ESPN DEPORTES","longName":"710 AM ESPN / 1330 AM ESPN DEPORTES"}]},"hTeam":{"streams":[{"language":"English","isOnAir":false,"streamId":""},{"language":"Spanish","isOnAir":false,"streamId":""}],"broadcasters":[{"shortName":"97.1 FM The Ticket","longName":"97.1 FM The Ticket"}]}}}}},{"seasonStageId":2,"seasonYear":"2019","leagueName":"standard","gameId":"0021901049","arena":{"name":"Scotiabank Arena","isDomestic":false,"city":"Toronto","stateAbbr":"ON","country":"Canada"},"isGameActivated":false,"statusNum":1,"extendedStatusNum":0,"startTimeEastern":"","startTimeUTC":"2020-03-22","startDateEastern":"20200322","homeStartDate":"20200322","homeStartTime":"","visitorStartDate":"20200322","visitorStartTime":"","gameUrlCode":"20200322/DENTOR","clock":"","isBuzzerBeater":false,"isPreviewArticleAvail":false,"isRecapArticleAvail":false,"nugget":{"text":""},"attendance":"","tickets":{"mobileApp":"https://a.data.nba.com/tickets/single/2019/0021901049/APP_TIX","desktopWeb":"https://a.data.nba.com/tickets/single/2019/0021901049/TEAM_SCH","mobileWeb":"https://a.data.nba.com/tickets/single/2019/0021901049/WEB_MWEB","leagGameInfo":"https://a.data.nba.com/tickets/single/2019/0021901049/LEAG_GAMEINFO","leagTix":"https://a.data.nba.com/tickets/single/2019/0021901049/LEAG_TIX"},"hasGameBookPdf":false,"isStartTimeTBD":true,"gameDuration":{"hours":"","minutes":""},"period":{"current":0,"type":0,"maxRegular":4,"isHalftime":false,"isEndOfPeriod":false},"vTeam":{"teamId":"1610612743","triCode":"DEN","win":"43","loss":"22","seriesWin":"1","seriesLoss":"0","score":"","linescore":[]},"hTeam":{"teamId":"1610612761","triCode":"TOR","win":"46","loss":"18","seriesWin":"0","seriesLoss":"1","score":"","linescore":[]},"watch":{"broadcast":{"broadcasters":{"national":[],"canadian":[{"shortName":"SN1","longName":"SN1"}],"vTeam":[{"shortName":"ALT","longName":"Altitude"}],"hTeam":[{"shortName":"SN1","longName":"SN1"}],"spanish_hTeam":[],"spanish_vTeam":[],"spanish_national":[]},"video":{"regionalBlackoutCodes":"torr_denr","canPurchase":false,"isLeaguePass":false,"isNationalBlackout":false,"isTNTOT":false,"isVR":false,"tntotIsOnAir":false,"isNextVR":false,"isNBAOnTNTVR":false,"isMagicLeap":false,"isOculusVenues":false,"streams":[{"streamType":"vTeam","isOnAir":false,"doesArchiveExist":false,"isArchiveAvailToWatch":false,"streamId":"","duration":0},{"streamType":"hTeam","isOnAir":false,"doesArchiveExist":false,"isArchiveAvailToWatch":false,"streamId":"","duration":0},{"streamType":"espanol_vTeam","isOnAir":false,"doesArchiveExist":false,"isArchiveAvailToWatch":false,"streamId":"","duration":0},{"streamType":"espanol_hTeam","isOnAir":false,"doesArchiveExist":false,"isArchiveAvailToWatch":false,"streamId":"","duration":0},{"streamType":"espanol_natl","isOnAir":false,"doesArchiveExist":false,"isArchiveAvailToWatch":false,"streamId":"","duration":0},{"streamType":"mobile","isOnAir":false,"doesArchiveExist":false,"isArchiveAvailToWatch":false,"streamId":"","duration":0},{"streamType":"condensed","isOnAir":false,"doesArchiveExist":false,"isArchiveAvailToWatch":false,"streamId":"","duration":0},{"streamType":"alt","isOnAir":false,"doesArchiveExist":false,"isArchiveAvailToWatch":false,"streamId":"","duration":0}],"deepLink":[]},"audio":{"national":{"streams":[{"language":"English","isOnAir":false,"streamId":""},{"language":"Spanish","isOnAir":false,"streamId":""}],"broadcasters":[]},"vTeam":{"streams":[{"language":"English","isOnAir":false,"streamId":""},{"language":"Spanish","isOnAir":false,"streamId":""}],"broadcasters":[{"shortName":"KKSE 92.5FM/950AM","longName":"KKSE 92.5FM/950AM"}]},"hTeam":{"streams":[{"language":"English","isOnAir":false,"streamId":""},{"language":"Spanish","isOnAir":false,"streamId":""}],"broadcasters":[{"shortName":"TSN Radio 1050 Toronto","longName":"TSN Radio 1050 Toronto"}]}}}}},{"seasonStageId":2,"seasonYear":"2019","leagueName":"standard","gameId":"0021901050","arena":{"name":"Target Center","isDomestic":true,"city":"Minneapolis","stateAbbr":"MN","country":"USA"},"isGameActivated":false,"statusNum":1,"extendedStatusNum":0,"startTimeEastern":"","startTimeUTC":"2020-03-22","startDateEastern":"20200322","homeStartDate":"20200322","homeStartTime":"","visitorStartDate":"20200322","visitorStartTime":"","gameUrlCode":"20200322/PORMIN","clock":"","isBuzzerBeater":false,"isPreviewArticleAvail":false,"isRecapArticleAvail":false,"nugget":{"text":""},"attendance":"","tickets":{"mobileApp":"https://a.data.nba.com/tickets/single/2019/0021901050/APP_TIX","desktopWeb":"https://a.data.nba.com/tickets/single/2019/0021901050/TEAM_SCH","mobileWeb":"https://a.data.nba.com/tickets/single/2019/0021901050/WEB_MWEB","leagGameInfo":"https://a.data.nba.com/tickets/single/2019/0021901050/LEAG_GAMEINFO","leagTix":"https://a.data.nba.com/tickets/single/2019/0021901050/LEAG_TIX"},"hasGameBookPdf":false,"isStartTimeTBD":true,"gameDuration":{"hours":"","minutes":""},"period":{"current":0,"type":0,"maxRegular":4,"isHalftime":false,"isEndOfPeriod":false},"vTeam":{"teamId":"1610612757","triCode":"POR","win":"29","loss":"37","seriesWin":"1","seriesLoss":"1","score":"","linescore":[]},"hTeam":{"teamId":"1610612750","triCode":"MIN","win":"19","loss":"45","seriesWin":"1","seriesLoss":"1","score":"","linescore":[]},"watch":{"broadcast":{"broadcasters":{"national":[],"canadian":[],"vTeam":[{"shortName":"NBCSNW/BP","longName":"NBCSNW/Blazers Pass"}],"hTeam":[{"shortName":"FSNTH","longName":"Fox Sports North"}],"spanish_hTeam":[],"spanish_vTeam":[],"spanish_national":[]},"video":{"regionalBlackoutCodes":"minr_porr","canPurchase":false,"isLeaguePass":false,"isNationalBlackout":false,"isTNTOT":false,"isVR":false,"tntotIsOnAir":false,"isNextVR":false,"isNBAOnTNTVR":false,"isMagicLeap":false,"isOculusVenues":false,"streams":[{"streamType":"vTeam","isOnAir":false,"doesArchiveExist":false,"isArchiveAvailToWatch":false,"streamId":"","duration":0},{"streamType":"hTeam","isOnAir":false,"doesArchiveExist":false,"isArchiveAvailToWatch":false,"streamId":"","duration":0},{"streamType":"espanol_vTeam","isOnAir":false,"doesArchiveExist":false,"isArchiveAvailToWatch":false,"streamId":"","duration":0},{"streamType":"espanol_hTeam","isOnAir":false,"doesArchiveExist":false,"isArchiveAvailToWatch":false,"streamId":"","duration":0},{"streamType":"espanol_natl","isOnAir":false,"doesArchiveExist":false,"isArchiveAvailToWatch":false,"streamId":"","duration":0},{"streamType":"mobile","isOnAir":false,"doesArchiveExist":false,"isArchiveAvailToWatch":false,"streamId":"","duration":0},{"streamType":"condensed","isOnAir":false,"doesArchiveExist":false,"isArchiveAvailToWatch":false,"streamId":"","duration":0},{"streamType":"alt","isOnAir":false,"doesArchiveExist":false,"isArchiveAvailToWatch":false,"streamId":"","duration":0}],"deepLink":[]},"audio":{"national":{"streams":[{"language":"English","isOnAir":false,"streamId":""},{"language":"Spanish","isOnAir":false,"streamId":""}],"broadcasters":[]},"vTeam":{"streams":[{"language":"English","isOnAir":false,"streamId":""},{"language":"Spanish","isOnAir":false,"streamId":""}],"broadcasters":[{"shortName":"Rip City Radio 620","longName":"Rip City Radio 620"}]},"hTeam":{"streams":[{"language":"English","isOnAir":false,"streamId":""},{"language":"Spanish","isOnAir":false,"streamId":""}],"broadcasters":[{"shortName":"830 WCCO","longName":"830 WCCO"}]}}}}},{"seasonStageId":2,"seasonYear":"2019","leagueName":"standard","gameId":"0021901051","arena":{"name":"Smoothie King Center","isDomestic":true,"city":"New Orleans","stateAbbr":"LA","country":"USA"},"isGameActivated":false,"statusNum":1,"extendedStatusNum":0,"startTimeEastern":"","startTimeUTC":"2020-03-22","startDateEastern":"20200322","homeStartDate":"20200322","homeStartTime":"","visitorStartDate":"20200322","visitorStartTime":"","gameUrlCode":"20200322/SACNOP","clock":"","isBuzzerBeater":false,"isPreviewArticleAvail":false,"isRecapArticleAvail":false,"nugget":{"text":""},"attendance":"","tickets":{"mobileApp":"https://a.data.nba.com/tickets/single/2019/0021901051/APP_TIX","desktopWeb":"https://a.data.nba.com/tickets/single/2019/0021901051/TEAM_SCH","mobileWeb":"https://a.data.nba.com/tickets/single/2019/0021901051/WEB_MWEB","leagGameInfo":"https://a.data.nba.com/tickets/single/2019/0021901051/LEAG_GAMEINFO","leagTix":"https://a.data.nba.com/tickets/single/2019/0021901051/LEAG_TIX"},"hasGameBookPdf":false,"isStartTimeTBD":true,"gameDuration":{"hours":"","minutes":""},"period":{"current":0,"type":0,"maxRegular":4,"isHalftime":false,"isEndOfPeriod":false},"vTeam":{"teamId":"1610612758","triCode":"SAC","win":"28","loss":"36","seriesWin":"0","seriesLoss":"1","score":"","linescore":[]},"hTeam":{"teamId":"1610612740","triCode":"NOP","win":"28","loss":"36","seriesWin":"1","seriesLoss":"0","score":"","linescore":[]},"watch":{"broadcast":{"broadcasters":{"national":[],"canadian":[],"vTeam":[{"shortName":"NBCSCA","longName":"NBC Sports California"}],"hTeam":[{"shortName":"FSNO","longName":"Fox Sports New Orleans"}],"spanish_hTeam":[],"spanish_vTeam":[],"spanish_national":[]},"video":{"regionalBlackoutCodes":"nopr_sacr","canPurchase":false,"isLeaguePass":false,"isNationalBlackout":false,"isTNTOT":false,"isVR":false,"tntotIsOnAir":false,"isNextVR":false,"isNBAOnTNTVR":false,"isMagicLeap":false,"isOculusVenues":false,"streams":[{"streamType":"vTeam","isOnAir":false,"doesArchiveExist":false,"isArchiveAvailToWatch":false,"streamId":"","duration":0},{"streamType":"hTeam","isOnAir":false,"doesArchiveExist":false,"isArchiveAvailToWatch":false,"streamId":"","duration":0},{"streamType":"espanol_vTeam","isOnAir":false,"doesArchiveExist":false,"isArchiveAvailToWatch":false,"streamId":"","duration":0},{"streamType":"espanol_hTeam","isOnAir":false,"doesArchiveExist":false,"isArchiveAvailToWatch":false,"streamId":"","duration":0},{"streamType":"espanol_natl","isOnAir":false,"doesArchiveExist":false,"isArchiveAvailToWatch":false,"streamId":"","duration":0},{"streamType":"mobile","isOnAir":false,"doesArchiveExist":false,"isArchiveAvailToWatch":false,"streamId":"","duration":0},{"streamType":"condensed","isOnAir":false,"doesArchiveExist":false,"isArchiveAvailToWatch":false,"streamId":"","duration":0},{"streamType":"alt","isOnAir":false,"doesArchiveExist":false,"isArchiveAvailToWatch":false,"streamId":"","duration":0}],"deepLink":[]},"audio":{"national":{"streams":[{"language":"English","isOnAir":false,"streamId":""},{"language":"Spanish","isOnAir":false,"streamId":""}],"broadcasters":[]},"vTeam":{"streams":[{"language":"English","isOnAir":false,"streamId":""},{"language":"Spanish","isOnAir":false,"streamId":""}],"broadcasters":[{"shortName":"KHTK Sports 1140 AM","longName":"KHTK Sports 1140 AM"}]},"hTeam":{"streams":[{"language":"English","isOnAir":false,"streamId":""},{"language":"Spanish","isOnAir":false,"streamId":""}],"broadcasters":[{"shortName":"ESPN 100.3FM","longName":"ESPN 100.3FM"}]}}}}},{"seasonStageId":2,"seasonYear":"2019","leagueName":"standard","gameId":"0021901052","arena":{"name":"AT&T Center","isDomestic":true,"city":"San Antonio","stateAbbr":"TX","country":"USA"},"isGameActivated":false,"statusNum":1,"extendedStatusNum":0,"startTimeEastern":"","startTimeUTC":"2020-03-22","startDateEastern":"20200322","homeStartDate":"20200322","homeStartTime":"","visitorStartDate":"20200322","visitorStartTime":"","gameUrlCode":"20200322/UTASAS","clock":"","isBuzzerBeater":false,"isPreviewArticleAvail":false,"isRecapArticleAvail":false,"nugget":{"text":""},"attendance":"","tickets":{"mobileApp":"https://a.data.nba.com/tickets/single/2019/0021901052/APP_TIX","desktopWeb":"https://a.data.nba.com/tickets/single/2019/0021901052/TEAM_SCH","mobileWeb":"https://a.data.nba.com/tickets/single/2019/0021901052/WEB_MWEB","leagGameInfo":"https://a.data.nba.com/tickets/single/2019/0021901052/LEAG_GAMEINFO","leagTix":"https://a.data.nba.com/tickets/single/2019/0021901052/LEAG_TIX"},"hasGameBookPdf":false,"isStartTimeTBD":true,"gameDuration":{"hours":"","minutes":""},"period":{"current":0,"type":0,"maxRegular":4,"isHalftime":false,"isEndOfPeriod":false},"vTeam":{"teamId":"1610612762","triCode":"UTA","win":"41","loss":"23","seriesWin":"0","seriesLoss":"2","score":"","linescore":[]},"hTeam":{"teamId":"1610612759","triCode":"SAS","win":"27","loss":"36","seriesWin":"2","seriesLoss":"0","score":"","linescore":[]},"watch":{"broadcast":{"broadcasters":{"national":[{"shortName":"NBA TV","longName":"NBA TV"}],"canadian":[{"shortName":"NBAC","longName":"NBA TV Canada"}],"vTeam":[{"shortName":"ATTSN-RM","longName":"AT&T Sportsnet - Rocky Mountain"}],"hTeam":[{"shortName":"FSSW-SA","longName":"Fox Sports Southwest - San Antonio"}],"spanish_hTeam":[],"spanish_vTeam":[],"spanish_national":[]},"video":{"regionalBlackoutCodes":"torr_sasr_utar","canPurchase":false,"isLeaguePass":false,"isNationalBlackout":true,"isTNTOT":false,"isVR":false,"tntotIsOnAir":false,"isNextVR":false,"isNBAOnTNTVR":false,"isMagicLeap":false,"isOculusVenues":false,"streams":[{"streamType":"vTeam","isOnAir":false,"doesArchiveExist":false,"isArchiveAvailToWatch":false,"streamId":"","duration":0},{"streamType":"hTeam","isOnAir":false,"doesArchiveExist":false,"isArchiveAvailToWatch":false,"streamId":"","duration":0},{"streamType":"espanol_vTeam","isOnAir":false,"doesArchiveExist":false,"isArchiveAvailToWatch":false,"streamId":"","duration":0},{"streamType":"espanol_hTeam","isOnAir":false,"doesArchiveExist":false,"isArchiveAvailToWatch":false,"streamId":"","duration":0},{"streamType":"espanol_natl","isOnAir":false,"doesArchiveExist":false,"isArchiveAvailToWatch":false,"streamId":"","duration":0},{"streamType":"mobile","isOnAir":false,"doesArchiveExist":false,"isArchiveAvailToWatch":false,"streamId":"","duration":0},{"streamType":"condensed","isOnAir":false,"doesArchiveExist":false,"isArchiveAvailToWatch":false,"streamId":"","duration":0},{"streamType":"alt","isOnAir":false,"doesArchiveExist":false,"isArchiveAvailToWatch":false,"streamId":"","duration":0}],"deepLink":[]},"audio":{"national":{"streams":[{"language":"English","isOnAir":false,"streamId":""},{"language":"Spanish","isOnAir":false,"streamId":""}],"broadcasters":[]},"vTeam":{"streams":[{"language":"English","isOnAir":false,"streamId":""},{"language":"Spanish","isOnAir":false,"streamId":""}],"broadcasters":[{"shortName":"97.5 FM | 1280 AM The Zone","longName":"97.5 FM | 1280 AM The Zone"}]},"hTeam":{"streams":[{"language":"English","isOnAir":false,"streamId":""},{"language":"Spanish","isOnAir":false,"streamId":""}],"broadcasters":[{"shortName":"WOAI 1200AM | S: KTXN 1350AM / 107.5FM H","longName":"WOAI 1200AM | S: KTXN 1350AM / 107.5FM H"}]}}}}}]}